{
  "nodes": {
    "0": {
      "alpha": 0,
      "actId": 3,
      "act": "Nop"
    },
    "1": {
      "alpha": 1,
      "actId": 4,
      "act": "RestrictAccPrivs"
    },
    "2": {
      "alpha": 2,
      "actId": 1,
      "act": "LockAccounts"
    },
    "3": {
      "alpha": 3,
      "actId": 2,
      "act": "LogIOCs",
      "start": true
    },
    "4": {
      "alpha": 4,
      "actId": 0,
      "act": "DecoyAccount"
    },
    "5": {
      "alpha": 5,
      "actId": 3,
      "act": "Nop"
    },
    "7": {
      "alpha": 7,
      "actId": 4,
      "act": "RestrictAccPrivs",
      "start": true
    },
    "8": {
      "alpha": 8,
      "actId": 1,
      "act": "LockAccounts"
    }
  },
  "edges": {
    "0": {
      "[(EndPtAlerts, file_enum)]": "0",
      "[(EndPtAlerts, file_write)]": "0",
      "[(EndPtAlerts, login_activity)]": "0",
      "[(EndPtAlerts, none)]": "0"
    },
    "1": {
      "[(EndPtAlerts, file_enum)]": "4",
      "[(EndPtAlerts, file_write)]": "4",
      "[(EndPtAlerts, login_activity)]": "4",
      "[(EndPtAlerts, none)]": "4"
    },
    "2": {
      "[(EndPtAlerts, file_enum)]": "8",
      "[(EndPtAlerts, file_write)]": "0",
      "[(EndPtAlerts, login_activity)]": "0",
      "[(EndPtAlerts, none)]": "0"
    },
    "3": {
      "[(EndPtAlerts, file_enum)]": "1",
      "[(EndPtAlerts, file_write)]": "1",
      "[(EndPtAlerts, login_activity)]": "1",
      "[(EndPtAlerts, none)]": "1"
    },
    "4": {
      "[(EndPtAlerts, file_enum)]": "0",
      "[(EndPtAlerts, file_write)]": "0",
      "[(EndPtAlerts, login_activity)]": "0",
      "[(EndPtAlerts, none)]": "0"
    },
    "5": {
      "[(EndPtAlerts, file_enum)]": "8",
      "[(EndPtAlerts, file_write)]": "2",
      "[(EndPtAlerts, login_activity)]": "8",
      "[(EndPtAlerts, none)]": "8"
    },
    "7": {
      "[(EndPtAlerts, file_enum)]": "5",
      "[(EndPtAlerts, file_write)]": "5",
      "[(EndPtAlerts, login_activity)]": "5",
      "[(EndPtAlerts, none)]": "5"
    },
    "8": {
      "[(EndPtAlerts, file_enum)]": "0",
      "[(EndPtAlerts, file_write)]": "0",
      "[(EndPtAlerts, login_activity)]": "0",
      "[(EndPtAlerts, none)]": "0"
    }
  }
}